itkit/__init__.py
itkit/criterions/__init__.py
itkit/criterions/segment.py
itkit/dataset/__init__.py
itkit/dataset/base.py
itkit/dataset/base_convert.py
itkit/dataset/AbdomenCT_1K/__init__.py
itkit/dataset/AbdomenCT_1K/convert_nii_mha.py
itkit/dataset/AbdomenCT_1K/meta.py
itkit/dataset/AbdomenCT_1K/mm_dataset.py
itkit/dataset/BraTs2024/convert_nii_mha.py
itkit/dataset/BraTs2024/meta.py
itkit/dataset/BraTs2024/mm_dataset.py
itkit/dataset/CTSpine1K/__init__.py
itkit/dataset/CTSpine1K/convert_nii_mha.py
itkit/dataset/CTSpine1K/convert_to_mha.py
itkit/dataset/CTSpine1K/meta.py
itkit/dataset/CTSpine1K/mm_dataset.py
itkit/dataset/CT_ORG/convert_nii_mha.py
itkit/dataset/CT_ORG/meta.py
itkit/dataset/CT_ORG/mm_dataset.py
itkit/dataset/FLARE_2022/convert_nii_mha.py
itkit/dataset/FLARE_2022/meta.py
itkit/dataset/FLARE_2022/mm_dataset.py
itkit/dataset/FLARE_2023/__init__.py
itkit/dataset/FLARE_2023/convert_nii_mha.py
itkit/dataset/FLARE_2023/meta.py
itkit/dataset/FLARE_2023/mm_dataset.py
itkit/dataset/GeneralDataset/convert_to_mha.py
itkit/dataset/GeneralDataset/mm_dataset.py
itkit/dataset/ImageTBAD/__init__.py
itkit/dataset/ImageTBAD/convert_nii_mha.py
itkit/dataset/ImageTBAD/meta.py
itkit/dataset/ImageTBAD/mm_dataset.py
itkit/dataset/KiTS23/__init__.py
itkit/dataset/KiTS23/convert_nii_mha.py
itkit/dataset/KiTS23/meta.py
itkit/dataset/KiTS23/mm_dataset.py
itkit/dataset/LUNA16/convert_mhd_mha.py
itkit/dataset/LUNA16/meta.py
itkit/dataset/LUNA16/mm_dataset.py
itkit/dataset/LiTS/__init__.py
itkit/dataset/LiTS/convert.py
itkit/dataset/LiTS/mm_dataset.py
itkit/dataset/SA_Med2D/DataProvider.py
itkit/dataset/SA_Med2D/DatasetBackend.py
itkit/dataset/SA_Med2D/DatasetInitialize.py
itkit/dataset/SA_Med2D/__init__.py
itkit/dataset/TCGA_Dataset/convert_to_mha.py
itkit/dataset/TCGA_Dataset/tcia_download.py
itkit/dataset/Totalsegmentator/AnalyzeClasses.py
itkit/dataset/Totalsegmentator/AnalyzeHUDistribution.py
itkit/dataset/Totalsegmentator/ClassRemap.py
itkit-3.4.0.dist-info/licenses/LICENSE
itkit-3.4.0.dist-info/METADATA
itkit-3.4.0.dist-info/WHEEL
itkit-3.4.0.dist-info/entry_points.txt
itkit-3.4.0.dist-info/top_level.txt
itkit-3.4.0.dist-info/RECORD
