Metadata-Version: 2.4
Name: itkit
Version: 3.4.0
Summary: mgam-ITKIT: Feasible Medical Image Operation based on SimpleITK API
License: MIT License
Requires-Python: >=3.10
License-File: LICENSE
Requires-Dist: numpy>=2.2.6
Requires-Dist: SimpleITK>=2.5.0
Requires-Dist: opencv-python-headless>=4.11
Requires-Dist: openpyxl
Requires-Dist: pandas
Requires-Dist: scikit-image
Requires-Dist: scikit-learn
Requires-Dist: scipy
Requires-Dist: future
Requires-Dist: tensorboard
Requires-Dist: orjson
Requires-Dist: tqdm
Requires-Dist: colorama
Requires-Dist: ml_collections
Requires-Dist: seaborn
Requires-Dist: matplotlib
Requires-Dist: matplotlib-inline
Requires-Dist: jupyter
Requires-Dist: colored
Requires-Dist: albumentations
Requires-Dist: ftfy
Requires-Dist: deprecated
Requires-Dist: pydantic
Requires-Dist: pydicom
Requires-Dist: pynrrd
Requires-Dist: nibabel
Requires-Dist: tcia_utils
Provides-Extra: dev
Requires-Dist: h5py; extra == "dev"
Requires-Dist: pylint-django; extra == "dev"
Requires-Dist: HolisticTraceAnalysis; extra == "dev"
Requires-Dist: pynvml; extra == "dev"
Requires-Dist: pytest; extra == "dev"
Requires-Dist: psutil; extra == "dev"
Requires-Dist: memory-profiler; extra == "dev"
Requires-Dist: types-colorama; extra == "dev"
Requires-Dist: types-tqdm; extra == "dev"
Requires-Dist: types-openpyxl; extra == "dev"
Requires-Dist: pandas-stubs; extra == "dev"
Requires-Dist: scipy-stubs; extra == "dev"
Requires-Dist: pyright; extra == "dev"
Requires-Dist: autopep8; extra == "dev"
Requires-Dist: black; extra == "dev"
Requires-Dist: isort; extra == "dev"
Requires-Dist: mypy; extra == "dev"
Provides-Extra: nvidia
Requires-Dist: onnx; extra == "nvidia"
Requires-Dist: onnxruntime; extra == "nvidia"
Requires-Dist: onnxruntime-gpu; extra == "nvidia"
Requires-Dist: onnx_graphsurgeon; extra == "nvidia"
Requires-Dist: polygraphy; extra == "nvidia"
Requires-Dist: tensorrt; extra == "nvidia"
Provides-Extra: pathology
Requires-Dist: opensdpc; extra == "pathology"
Requires-Dist: openslide-python; extra == "pathology"
Requires-Dist: openslide-bin; extra == "pathology"
Provides-Extra: pytorch
Requires-Dist: lightning; extra == "pytorch"
Requires-Dist: timm; extra == "pytorch"
Requires-Dist: deepspeed; extra == "pytorch"
Provides-Extra: mm
Requires-Dist: ftfy; extra == "mm"
Requires-Dist: regex; extra == "mm"
Provides-Extra: gui
Requires-Dist: PyQt6; extra == "gui"
Dynamic: license-file
